{
  "components" : {
    "schemas" : {
      "AccountDeletePreviewDto" : {
        "properties" : {
          "accountId" : {
            "format" : "int64",
            "type" : "integer"
          },
          "transactionCount" : {
            "format" : "int64",
            "type" : "integer"
          }
        },
        "type" : "object"
      },
      "AccountResponse" : {
        "properties" : {
          "accountType" : {
            "enum" : [ "CASH", "BANK", "CREDIT_CARD", "SAVINGS", "OTHER" ],
            "type" : "string"
          },
          "createdAt" : {
            "format" : "date-time",
            "type" : "string"
          },
          "currency" : {
            "type" : "string"
          },
          "currentBalance" : {
            "type" : "number"
          },
          "id" : {
            "format" : "int64",
            "type" : "integer"
          },
          "initialBalance" : {
            "type" : "number"
          },
          "name" : {
            "type" : "string"
          },
          "updatedAt" : {
            "format" : "date-time",
            "type" : "string"
          }
        },
        "type" : "object"
      },
      "ActivityEventResponse" : {
        "properties" : {
          "action" : {
            "type" : "string"
          },
          "correlationId" : {
            "type" : "string"
          },
          "id" : {
            "format" : "int64",
            "type" : "integer"
          },
          "meta" : {
            "additionalProperties" : {
              "type" : "object"
            },
            "type" : "object"
          },
          "ts" : {
            "format" : "date-time",
            "type" : "string"
          }
        },
        "type" : "object"
      },
      "AgentDecisionRequest" : {
        "properties" : {
          "approve" : {
            "type" : "boolean"
          },
          "proposals" : {
            "items" : {
              "$ref" : "#/components/schemas/ProposalDto"
            },
            "type" : "array"
          }
        },
        "required" : [ "approve" ],
        "type" : "object"
      },
      "AgentRunDetailResponse" : {
        "properties" : {
          "createdAt" : {
            "format" : "date-time",
            "type" : "string"
          },
          "createdTransactionIds" : {
            "items" : {
              "format" : "int64",
              "type" : "integer"
            },
            "type" : "array"
          },
          "extraction" : {
            "additionalProperties" : {
              "type" : "object"
            },
            "type" : "object"
          },
          "failureReason" : {
            "type" : "string"
          },
          "id" : {
            "format" : "int64",
            "type" : "integer"
          },
          "proposals" : {
            "items" : {
              "$ref" : "#/components/schemas/ProposalDto"
            },
            "type" : "array"
          },
          "retryable" : {
            "type" : "boolean"
          },
          "status" : {
            "enum" : [ "EXTRACTING", "AWAITING_REVIEW", "COMMITTED", "REJECTED", "FAILED" ],
            "type" : "string"
          },
          "updatedAt" : {
            "format" : "date-time",
            "type" : "string"
          },
          "vaultDocumentId" : {
            "type" : "string"
          }
        },
        "type" : "object"
      },
      "AgentRunSummaryResponse" : {
        "properties" : {
          "createdAt" : {
            "format" : "date-time",
            "type" : "string"
          },
          "id" : {
            "format" : "int64",
            "type" : "integer"
          },
          "status" : {
            "enum" : [ "EXTRACTING", "AWAITING_REVIEW", "COMMITTED", "REJECTED", "FAILED" ],
            "type" : "string"
          },
          "updatedAt" : {
            "format" : "date-time",
            "type" : "string"
          },
          "vaultDocumentId" : {
            "type" : "string"
          }
        },
        "type" : "object"
      },
      "ApiTokenResponse" : {
        "properties" : {
          "createdAt" : {
            "format" : "date-time",
            "type" : "string"
          },
          "expiresAt" : {
            "format" : "date-time",
            "type" : "string"
          },
          "id" : {
            "format" : "int64",
            "type" : "integer"
          },
          "lastUsedAt" : {
            "format" : "date-time",
            "type" : "string"
          },
          "name" : {
            "type" : "string"
          },
          "revoked" : {
            "type" : "boolean"
          },
          "scope" : {
            "enum" : [ "READ", "WRITE" ],
            "type" : "string"
          },
          "tokenPrefix" : {
            "type" : "string"
          }
        },
        "type" : "object"
      },
      "BatchTransactionRequest" : {
        "properties" : {
          "transactions" : {
            "items" : {
              "$ref" : "#/components/schemas/BatchTransactionRowRequest"
            },
            "maxItems" : 100,
            "minItems" : 0,
            "type" : "array"
          }
        },
        "required" : [ "transactions" ],
        "type" : "object"
      },
      "BatchTransactionResponse" : {
        "properties" : {
          "results" : {
            "items" : {
              "$ref" : "#/components/schemas/BatchTransactionRowResult"
            },
            "type" : "array"
          }
        },
        "type" : "object"
      },
      "BatchTransactionRowRequest" : {
        "properties" : {
          "clientRequestId" : {
            "maxLength" : 128,
            "minLength" : 16,
            "pattern" : "^[A-Za-z0-9_-]+$",
            "type" : "string"
          },
          "transaction" : {
            "$ref" : "#/components/schemas/CreateTransactionRequest"
          }
        },
        "required" : [ "clientRequestId", "transaction" ],
        "type" : "object"
      },
      "BatchTransactionRowResult" : {
        "properties" : {
          "clientRequestId" : {
            "type" : "string"
          },
          "error" : {
            "type" : "string"
          },
          "rowIndex" : {
            "format" : "int32",
            "type" : "integer"
          },
          "status" : {
            "enum" : [ "CREATED", "REPLAYED", "CONFLICT", "FAILED" ],
            "type" : "string"
          },
          "transaction" : {
            "$ref" : "#/components/schemas/TransactionResponse"
          }
        },
        "type" : "object"
      },
      "BudgetHistoryDto" : {
        "properties" : {
          "amountLimit" : {
            "type" : "number"
          },
          "budgetId" : {
            "format" : "int64",
            "type" : "integer"
          },
          "categoryId" : {
            "format" : "int64",
            "type" : "integer"
          },
          "categoryName" : {
            "type" : "string"
          },
          "currency" : {
            "type" : "string"
          },
          "overBudget" : {
            "type" : "boolean"
          },
          "percentUsed" : {
            "type" : "number"
          },
          "period" : {
            "enum" : [ "MONTHLY", "YEARLY" ],
            "type" : "string"
          },
          "periodEnd" : {
            "format" : "date",
            "type" : "string"
          },
          "periodStart" : {
            "format" : "date",
            "type" : "string"
          },
          "remaining" : {
            "type" : "number"
          },
          "spent" : {
            "type" : "number"
          }
        },
        "type" : "object"
      },
      "BudgetProgressDto" : {
        "properties" : {
          "budgetId" : {
            "format" : "int64",
            "type" : "integer"
          },
          "budgetName" : {
            "type" : "string"
          },
          "categoryName" : {
            "type" : "string"
          },
          "currency" : {
            "type" : "string"
          },
          "limitAmount" : {
            "type" : "number"
          },
          "overBudget" : {
            "type" : "boolean"
          },
          "percentUsed" : {
            "type" : "number"
          },
          "remaining" : {
            "type" : "number"
          },
          "spent" : {
            "type" : "number"
          }
        },
        "type" : "object"
      },
      "BudgetResponse" : {
        "properties" : {
          "amountLimit" : {
            "type" : "number"
          },
          "categoryId" : {
            "format" : "int64",
            "type" : "integer"
          },
          "categoryName" : {
            "type" : "string"
          },
          "createdAt" : {
            "format" : "date-time",
            "type" : "string"
          },
          "currency" : {
            "type" : "string"
          },
          "id" : {
            "format" : "int64",
            "type" : "integer"
          },
          "overBudget" : {
            "type" : "boolean"
          },
          "percentUsed" : {
            "type" : "number"
          },
          "period" : {
            "enum" : [ "MONTHLY", "YEARLY" ],
            "type" : "string"
          },
          "remaining" : {
            "type" : "number"
          },
          "spent" : {
            "type" : "number"
          },
          "startDate" : {
            "format" : "date",
            "type" : "string"
          },
          "updatedAt" : {
            "format" : "date-time",
            "type" : "string"
          }
        },
        "type" : "object"
      },
      "CategoryResponse" : {
        "properties" : {
          "createdAt" : {
            "format" : "date-time",
            "type" : "string"
          },
          "id" : {
            "format" : "int64",
            "type" : "integer"
          },
          "name" : {
            "type" : "string"
          },
          "system" : {
            "type" : "boolean"
          },
          "transactionType" : {
            "enum" : [ "INCOME", "EXPENSE", "TRANSFER" ],
            "type" : "string"
          }
        },
        "type" : "object"
      },
      "ConfirmImportRequest" : {
        "properties" : {
          "selectedDedupKeys" : {
            "items" : {
              "type" : "string"
            },
            "type" : "array"
          }
        },
        "required" : [ "selectedDedupKeys" ],
        "type" : "object"
      },
      "ConfirmImportResponse" : {
        "properties" : {
          "created" : {
            "format" : "int32",
            "type" : "integer"
          },
          "duplicate" : {
            "format" : "int32",
            "type" : "integer"
          },
          "failed" : {
            "format" : "int32",
            "type" : "integer"
          },
          "rows" : {
            "items" : {
              "$ref" : "#/components/schemas/RowResult"
            },
            "type" : "array"
          }
        },
        "type" : "object"
      },
      "ConvertResponse" : {
        "properties" : {
          "amount" : {
            "type" : "number"
          },
          "asOf" : {
            "format" : "date-time",
            "type" : "string"
          },
          "convertedAmount" : {
            "type" : "number"
          },
          "from" : {
            "type" : "string"
          },
          "rate" : {
            "type" : "number"
          },
          "to" : {
            "type" : "string"
          }
        },
        "type" : "object"
      },
      "ConvertedOverviewDto" : {
        "properties" : {
          "asOf" : {
            "format" : "date-time",
            "type" : "string"
          },
          "excludedCurrencies" : {
            "items" : {
              "$ref" : "#/components/schemas/ExcludedCurrencyDto"
            },
            "type" : "array"
          },
          "rates" : {
            "items" : {
              "$ref" : "#/components/schemas/RateUsedDto"
            },
            "type" : "array"
          },
          "ratesUnavailable" : {
            "type" : "boolean"
          },
          "spending" : {
            "items" : {
              "$ref" : "#/components/schemas/ConvertedSpendingDto"
            },
            "type" : "array"
          },
          "stale" : {
            "type" : "boolean"
          },
          "targetCurrency" : {
            "type" : "string"
          },
          "trend" : {
            "items" : {
              "$ref" : "#/components/schemas/ConvertedTrendDto"
            },
            "type" : "array"
          }
        },
        "type" : "object"
      },
      "ConvertedSpendingDto" : {
        "properties" : {
          "categoryId" : {
            "format" : "int64",
            "type" : "integer"
          },
          "categoryName" : {
            "type" : "string"
          },
          "totalAmount" : {
            "type" : "number"
          },
          "transactionCount" : {
            "format" : "int64",
            "type" : "integer"
          }
        },
        "type" : "object"
      },
      "ConvertedTrendDto" : {
        "properties" : {
          "expense" : {
            "type" : "number"
          },
          "income" : {
            "type" : "number"
          },
          "month" : {
            "format" : "int32",
            "type" : "integer"
          },
          "net" : {
            "type" : "number"
          },
          "year" : {
            "format" : "int32",
            "type" : "integer"
          }
        },
        "type" : "object"
      },
      "CreateAccountRequest" : {
        "properties" : {
          "accountType" : {
            "enum" : [ "CASH", "BANK", "CREDIT_CARD", "SAVINGS", "OTHER" ],
            "type" : "string"
          },
          "currency" : {
            "pattern" : "^[A-Z]{3}$",
            "type" : "string"
          },
          "initialBalance" : {
            "exclusiveMinimum" : false,
            "minimum" : 0.0,
            "type" : "number"
          },
          "name" : {
            "maxLength" : 255,
            "minLength" : 0,
            "type" : "string"
          }
        },
        "required" : [ "accountType", "currency", "name" ],
        "type" : "object"
      },
      "CreateApiTokenRequest" : {
        "properties" : {
          "expiryDays" : {
            "format" : "int32",
            "type" : "integer"
          },
          "name" : {
            "maxLength" : 100,
            "minLength" : 0,
            "type" : "string"
          },
          "scope" : {
            "enum" : [ "READ", "WRITE" ],
            "type" : "string"
          }
        },
        "required" : [ "expiryDays", "name", "scope" ],
        "type" : "object"
      },
      "CreateBudgetRequest" : {
        "properties" : {
          "amountLimit" : {
            "exclusiveMinimum" : false,
            "minimum" : 0.01,
            "type" : "number"
          },
          "categoryId" : {
            "format" : "int64",
            "type" : "integer"
          },
          "currency" : {
            "pattern" : "^[A-Z]{3}$",
            "type" : "string"
          },
          "period" : {
            "enum" : [ "MONTHLY", "YEARLY" ],
            "type" : "string"
          },
          "startDate" : {
            "format" : "date",
            "type" : "string"
          }
        },
        "required" : [ "amountLimit", "categoryId", "currency", "period", "startDate" ],
        "type" : "object"
      },
      "CreateCategoryRequest" : {
        "properties" : {
          "name" : {
            "maxLength" : 100,
            "minLength" : 0,
            "type" : "string"
          },
          "transactionType" : {
            "enum" : [ "INCOME", "EXPENSE", "TRANSFER" ],
            "type" : "string"
          }
        },
        "required" : [ "name", "transactionType" ],
        "type" : "object"
      },
      "CreateRecurringRequest" : {
        "properties" : {
          "accountId" : {
            "format" : "int64",
            "type" : "integer"
          },
          "amount" : {
            "exclusiveMinimum" : false,
            "minimum" : 0.01,
            "type" : "number"
          },
          "categoryId" : {
            "format" : "int64",
            "type" : "integer"
          },
          "endDate" : {
            "format" : "date",
            "type" : "string"
          },
          "frequency" : {
            "enum" : [ "DAILY", "WEEKLY", "MONTHLY", "YEARLY" ],
            "type" : "string"
          },
          "intervalValue" : {
            "format" : "int32",
            "minimum" : 1,
            "type" : "integer"
          },
          "maxOccurrences" : {
            "format" : "int32",
            "type" : "integer"
          },
          "note" : {
            "maxLength" : 2000,
            "minLength" : 0,
            "type" : "string"
          },
          "startDate" : {
            "format" : "date",
            "type" : "string"
          },
          "transactionType" : {
            "enum" : [ "INCOME", "EXPENSE", "TRANSFER" ],
            "type" : "string"
          }
        },
        "required" : [ "accountId", "amount", "frequency", "startDate", "transactionType" ],
        "type" : "object"
      },
      "CreateTransactionRequest" : {
        "properties" : {
          "accountId" : {
            "format" : "int64",
            "type" : "integer"
          },
          "amount" : {
            "exclusiveMinimum" : false,
            "minimum" : 0.01,
            "type" : "number"
          },
          "categoryId" : {
            "format" : "int64",
            "type" : "integer"
          },
          "destinationAmount" : {
            "exclusiveMinimum" : false,
            "minimum" : 0.01,
            "type" : "number"
          },
          "note" : {
            "maxLength" : 2000,
            "minLength" : 0,
            "type" : "string"
          },
          "transactionDate" : {
            "format" : "date",
            "type" : "string"
          },
          "transactionType" : {
            "enum" : [ "INCOME", "EXPENSE", "TRANSFER" ],
            "type" : "string"
          },
          "transferAccountId" : {
            "format" : "int64",
            "type" : "integer"
          }
        },
        "required" : [ "accountId", "amount", "transactionDate", "transactionType" ],
        "type" : "object"
      },
      "CreatedApiTokenResponse" : {
        "properties" : {
          "plaintextToken" : {
            "type" : "string"
          },
          "token" : {
            "$ref" : "#/components/schemas/ApiTokenResponse"
          }
        },
        "type" : "object"
      },
      "ExcludedCurrencyDto" : {
        "properties" : {
          "currency" : {
            "type" : "string"
          },
          "nativeAmount" : {
            "type" : "number"
          }
        },
        "type" : "object"
      },
      "FailAgentRunRequest" : {
        "properties" : {
          "reason" : {
            "type" : "string"
          },
          "retryable" : {
            "type" : "boolean"
          }
        },
        "type" : "object"
      },
      "IncomeExpenseTrendDto" : {
        "properties" : {
          "currency" : {
            "type" : "string"
          },
          "month" : {
            "format" : "int32",
            "type" : "integer"
          },
          "net" : {
            "type" : "number"
          },
          "totalExpense" : {
            "type" : "number"
          },
          "totalIncome" : {
            "type" : "number"
          },
          "year" : {
            "format" : "int32",
            "type" : "integer"
          }
        },
        "type" : "object"
      },
      "IncomingTransferTotalDto" : {
        "properties" : {
          "accountId" : {
            "format" : "int64",
            "type" : "integer"
          },
          "total" : {
            "type" : "number"
          }
        },
        "type" : "object"
      },
      "LoginRequest" : {
        "properties" : {
          "email" : {
            "type" : "string"
          },
          "password" : {
            "type" : "string"
          }
        },
        "required" : [ "email", "password" ],
        "type" : "object"
      },
      "MutationWarning" : {
        "properties" : {
          "accountId" : {
            "format" : "int64",
            "type" : "integer"
          },
          "code" : {
            "type" : "string"
          },
          "message" : {
            "type" : "string"
          }
        },
        "type" : "object"
      },
      "PageActivityEventResponse" : {
        "properties" : {
          "content" : {
            "items" : {
              "$ref" : "#/components/schemas/ActivityEventResponse"
            },
            "type" : "array"
          },
          "empty" : {
            "type" : "boolean"
          },
          "first" : {
            "type" : "boolean"
          },
          "last" : {
            "type" : "boolean"
          },
          "number" : {
            "format" : "int32",
            "type" : "integer"
          },
          "numberOfElements" : {
            "format" : "int32",
            "type" : "integer"
          },
          "pageable" : {
            "$ref" : "#/components/schemas/PageableObject"
          },
          "size" : {
            "format" : "int32",
            "type" : "integer"
          },
          "sort" : {
            "items" : {
              "$ref" : "#/components/schemas/SortObject"
            },
            "type" : "array"
          },
          "totalElements" : {
            "format" : "int64",
            "type" : "integer"
          },
          "totalPages" : {
            "format" : "int32",
            "type" : "integer"
          }
        },
        "type" : "object"
      },
      "PageResponseTransactionResponse" : {
        "properties" : {
          "content" : {
            "items" : {
              "$ref" : "#/components/schemas/TransactionResponse"
            },
            "type" : "array"
          },
          "last" : {
            "type" : "boolean"
          },
          "page" : {
            "format" : "int32",
            "type" : "integer"
          },
          "size" : {
            "format" : "int32",
            "type" : "integer"
          },
          "totalElements" : {
            "format" : "int64",
            "type" : "integer"
          },
          "totalPages" : {
            "format" : "int32",
            "type" : "integer"
          }
        },
        "type" : "object"
      },
      "PageVaultDocumentResponse" : {
        "properties" : {
          "content" : {
            "items" : {
              "$ref" : "#/components/schemas/VaultDocumentResponse"
            },
            "type" : "array"
          },
          "empty" : {
            "type" : "boolean"
          },
          "first" : {
            "type" : "boolean"
          },
          "last" : {
            "type" : "boolean"
          },
          "number" : {
            "format" : "int32",
            "type" : "integer"
          },
          "numberOfElements" : {
            "format" : "int32",
            "type" : "integer"
          },
          "pageable" : {
            "$ref" : "#/components/schemas/PageableObject"
          },
          "size" : {
            "format" : "int32",
            "type" : "integer"
          },
          "sort" : {
            "items" : {
              "$ref" : "#/components/schemas/SortObject"
            },
            "type" : "array"
          },
          "totalElements" : {
            "format" : "int64",
            "type" : "integer"
          },
          "totalPages" : {
            "format" : "int32",
            "type" : "integer"
          }
        },
        "type" : "object"
      },
      "Pageable" : {
        "properties" : {
          "page" : {
            "format" : "int32",
            "minimum" : 0,
            "type" : "integer"
          },
          "size" : {
            "format" : "int32",
            "minimum" : 1,
            "type" : "integer"
          },
          "sort" : {
            "items" : {
              "type" : "string"
            },
            "type" : "array"
          }
        },
        "type" : "object"
      },
      "PageableObject" : {
        "properties" : {
          "offset" : {
            "format" : "int64",
            "type" : "integer"
          },
          "pageNumber" : {
            "format" : "int32",
            "type" : "integer"
          },
          "pageSize" : {
            "format" : "int32",
            "type" : "integer"
          },
          "paged" : {
            "type" : "boolean"
          },
          "sort" : {
            "items" : {
              "$ref" : "#/components/schemas/SortObject"
            },
            "type" : "array"
          },
          "unpaged" : {
            "type" : "boolean"
          }
        },
        "type" : "object"
      },
      "ProposalDto" : {
        "properties" : {
          "accountId" : {
            "format" : "int64",
            "type" : "integer"
          },
          "amount" : {
            "type" : "number"
          },
          "categoryId" : {
            "format" : "int64",
            "type" : "integer"
          },
          "currency" : {
            "type" : "string"
          },
          "date" : {
            "format" : "date",
            "type" : "string"
          },
          "description" : {
            "type" : "string"
          },
          "excluded" : {
            "type" : "boolean"
          },
          "flags" : {
            "items" : {
              "type" : "string"
            },
            "type" : "array"
          },
          "merchant" : {
            "type" : "string"
          }
        },
        "required" : [ "amount", "currency", "date", "merchant" ],
        "type" : "object"
      },
      "RateUsedDto" : {
        "properties" : {
          "from" : {
            "type" : "string"
          },
          "rate" : {
            "type" : "number"
          },
          "to" : {
            "type" : "string"
          }
        },
        "type" : "object"
      },
      "RecurringResponse" : {
        "properties" : {
          "accountId" : {
            "format" : "int64",
            "type" : "integer"
          },
          "accountName" : {
            "type" : "string"
          },
          "active" : {
            "type" : "boolean"
          },
          "amount" : {
            "type" : "number"
          },
          "categoryId" : {
            "format" : "int64",
            "type" : "integer"
          },
          "categoryName" : {
            "type" : "string"
          },
          "createdAt" : {
            "format" : "date-time",
            "type" : "string"
          },
          "endDate" : {
            "format" : "date",
            "type" : "string"
          },
          "frequency" : {
            "enum" : [ "DAILY", "WEEKLY", "MONTHLY", "YEARLY" ],
            "type" : "string"
          },
          "id" : {
            "format" : "int64",
            "type" : "integer"
          },
          "intervalValue" : {
            "format" : "int32",
            "type" : "integer"
          },
          "maxOccurrences" : {
            "format" : "int32",
            "type" : "integer"
          },
          "nextRunDate" : {
            "format" : "date",
            "type" : "string"
          },
          "note" : {
            "type" : "string"
          },
          "occurrencesCount" : {
            "format" : "int32",
            "type" : "integer"
          },
          "startDate" : {
            "format" : "date",
            "type" : "string"
          },
          "transactionType" : {
            "enum" : [ "INCOME", "EXPENSE", "TRANSFER" ],
            "type" : "string"
          },
          "updatedAt" : {
            "format" : "date-time",
            "type" : "string"
          }
        },
        "type" : "object"
      },
      "RefreshRequest" : {
        "properties" : {
          "refreshToken" : {
            "type" : "string"
          }
        },
        "required" : [ "refreshToken" ],
        "type" : "object"
      },
      "RegisterRequest" : {
        "properties" : {
          "email" : {
            "type" : "string"
          },
          "firstName" : {
            "maxLength" : 100,
            "minLength" : 0,
            "type" : "string"
          },
          "lastName" : {
            "maxLength" : 100,
            "minLength" : 0,
            "type" : "string"
          },
          "password" : {
            "maxLength" : 2147483647,
            "minLength" : 8,
            "type" : "string"
          }
        },
        "required" : [ "email", "firstName", "lastName", "password" ],
        "type" : "object"
      },
      "RowResult" : {
        "properties" : {
          "dedupKey" : {
            "type" : "string"
          },
          "error" : {
            "type" : "string"
          },
          "status" : {
            "type" : "string"
          },
          "transactionId" : {
            "format" : "int64",
            "type" : "integer"
          }
        },
        "type" : "object"
      },
      "SortObject" : {
        "properties" : {
          "ascending" : {
            "type" : "boolean"
          },
          "direction" : {
            "type" : "string"
          },
          "ignoreCase" : {
            "type" : "boolean"
          },
          "nullHandling" : {
            "type" : "string"
          },
          "property" : {
            "type" : "string"
          }
        },
        "type" : "object"
      },
      "SpendingByCategoryDto" : {
        "properties" : {
          "categoryId" : {
            "format" : "int64",
            "type" : "integer"
          },
          "categoryName" : {
            "type" : "string"
          },
          "currency" : {
            "type" : "string"
          },
          "total" : {
            "type" : "number"
          },
          "transactionCount" : {
            "format" : "int64",
            "type" : "integer"
          }
        },
        "type" : "object"
      },
      "StagedRowResponse" : {
        "properties" : {
          "amount" : {
            "type" : "string"
          },
          "date" : {
            "type" : "string"
          },
          "dedupKey" : {
            "type" : "string"
          },
          "description" : {
            "type" : "string"
          },
          "type" : {
            "type" : "string"
          }
        },
        "type" : "object"
      },
      "StartAgentRunRequest" : {
        "properties" : {
          "vaultDocumentId" : {
            "type" : "string"
          }
        },
        "required" : [ "vaultDocumentId" ],
        "type" : "object"
      },
      "SubmitProposalsRequest" : {
        "properties" : {
          "extraction" : {
            "additionalProperties" : {
              "type" : "object"
            },
            "type" : "object"
          },
          "proposals" : {
            "items" : {
              "$ref" : "#/components/schemas/ProposalDto"
            },
            "type" : "array"
          }
        },
        "required" : [ "extraction", "proposals" ],
        "type" : "object"
      },
      "TokenResponse" : {
        "properties" : {
          "accessToken" : {
            "type" : "string"
          },
          "expiresIn" : {
            "format" : "int64",
            "type" : "integer"
          },
          "refreshToken" : {
            "type" : "string"
          },
          "tokenType" : {
            "type" : "string"
          },
          "user" : {
            "$ref" : "#/components/schemas/UserInfo"
          }
        },
        "type" : "object"
      },
      "TransactionResponse" : {
        "properties" : {
          "accountId" : {
            "format" : "int64",
            "type" : "integer"
          },
          "accountName" : {
            "type" : "string"
          },
          "amount" : {
            "type" : "number"
          },
          "categoryId" : {
            "format" : "int64",
            "type" : "integer"
          },
          "categoryName" : {
            "type" : "string"
          },
          "createdAt" : {
            "format" : "date-time",
            "type" : "string"
          },
          "currency" : {
            "type" : "string"
          },
          "destinationAmount" : {
            "type" : "number"
          },
          "destinationCurrency" : {
            "type" : "string"
          },
          "id" : {
            "format" : "int64",
            "type" : "integer"
          },
          "note" : {
            "type" : "string"
          },
          "recurringId" : {
            "format" : "int64",
            "type" : "integer"
          },
          "sourceDocumentId" : {
            "type" : "string"
          },
          "transactionDate" : {
            "format" : "date",
            "type" : "string"
          },
          "transactionType" : {
            "enum" : [ "INCOME", "EXPENSE", "TRANSFER" ],
            "type" : "string"
          },
          "transferAccountId" : {
            "format" : "int64",
            "type" : "integer"
          },
          "transferAccountName" : {
            "type" : "string"
          },
          "updatedAt" : {
            "format" : "date-time",
            "type" : "string"
          },
          "warnings" : {
            "items" : {
              "$ref" : "#/components/schemas/MutationWarning"
            },
            "type" : "array"
          }
        },
        "type" : "object"
      },
      "UpdateAccountRequest" : {
        "properties" : {
          "accountType" : {
            "enum" : [ "CASH", "BANK", "CREDIT_CARD", "SAVINGS", "OTHER" ],
            "type" : "string"
          },
          "currency" : {
            "pattern" : "^[A-Z]{3}$",
            "type" : "string"
          },
          "initialBalance" : {
            "exclusiveMinimum" : false,
            "minimum" : 0.0,
            "type" : "number"
          },
          "name" : {
            "maxLength" : 255,
            "minLength" : 0,
            "type" : "string"
          }
        },
        "type" : "object"
      },
      "UpdateBudgetRequest" : {
        "properties" : {
          "amountLimit" : {
            "exclusiveMinimum" : false,
            "minimum" : 0.01,
            "type" : "number"
          },
          "period" : {
            "enum" : [ "MONTHLY", "YEARLY" ],
            "type" : "string"
          }
        },
        "type" : "object"
      },
      "UpdateCategoryRequest" : {
        "properties" : {
          "name" : {
            "maxLength" : 100,
            "minLength" : 0,
            "type" : "string"
          },
          "transactionType" : {
            "enum" : [ "INCOME", "EXPENSE", "TRANSFER" ],
            "type" : "string"
          }
        },
        "required" : [ "name" ],
        "type" : "object"
      },
      "UpdateChangelogSeenRequest" : {
        "properties" : {
          "version" : {
            "format" : "int32",
            "type" : "integer"
          }
        },
        "required" : [ "version" ],
        "type" : "object"
      },
      "UpdateLanguageRequest" : {
        "properties" : {
          "language" : {
            "pattern" : "^(en|vi|de|zh)$",
            "type" : "string"
          }
        },
        "required" : [ "language" ],
        "type" : "object"
      },
      "UpdateTransactionRequest" : {
        "properties" : {
          "amount" : {
            "exclusiveMinimum" : false,
            "minimum" : 0.01,
            "type" : "number"
          },
          "categoryId" : {
            "format" : "int64",
            "type" : "integer"
          },
          "destinationAmount" : {
            "exclusiveMinimum" : false,
            "minimum" : 0.01,
            "type" : "number"
          },
          "note" : {
            "maxLength" : 2000,
            "minLength" : 0,
            "type" : "string"
          },
          "transactionDate" : {
            "format" : "date",
            "type" : "string"
          }
        },
        "type" : "object"
      },
      "UserInfo" : {
        "properties" : {
          "email" : {
            "type" : "string"
          },
          "firstName" : {
            "type" : "string"
          },
          "id" : {
            "format" : "int64",
            "type" : "integer"
          },
          "lastName" : {
            "type" : "string"
          },
          "lastSeenChangelogVersion" : {
            "format" : "int32",
            "type" : "integer"
          },
          "preferredLanguage" : {
            "type" : "string"
          }
        },
        "type" : "object"
      },
      "VaultDocumentResponse" : {
        "properties" : {
          "capturedAt" : {
            "format" : "date-time",
            "type" : "string"
          },
          "hasBinary" : {
            "type" : "boolean"
          },
          "id" : {
            "type" : "string"
          },
          "ingestionStatus" : {
            "enum" : [ "EXTRACTING", "AWAITING_REVIEW", "COMMITTED", "REJECTED", "FAILED" ],
            "type" : "string"
          },
          "originalFilename" : {
            "type" : "string"
          },
          "payload" : {
            "additionalProperties" : {
              "type" : "object"
            },
            "type" : "object"
          },
          "source" : {
            "type" : "string"
          },
          "status" : {
            "enum" : [ "STAGED", "CONFIRMING", "ACTIVE" ],
            "type" : "string"
          },
          "transactionId" : {
            "format" : "int64",
            "type" : "integer"
          },
          "type" : {
            "enum" : [ "RECEIPT", "STATEMENT" ],
            "type" : "string"
          }
        },
        "type" : "object"
      },
      "VaultSearchRequest" : {
        "properties" : {
          "from" : {
            "format" : "date-time",
            "type" : "string"
          },
          "lineItemText" : {
            "type" : "string"
          },
          "maxLineItemAmount" : {
            "type" : "number"
          },
          "merchant" : {
            "type" : "string"
          },
          "to" : {
            "format" : "date-time",
            "type" : "string"
          }
        },
        "type" : "object"
      }
    },
    "securitySchemes" : {
      "bearerAuth" : {
        "bearerFormat" : "JWT",
        "description" : "Provide a valid JWT access token obtained from /api/v1/auth/login",
        "scheme" : "bearer",
        "type" : "http"
      }
    }
  },
  "info" : {
    "description" : "Personal finance management — accounts, transactions, budgets, analytics",
    "title" : "Fintrack API",
    "version" : "1.0"
  },
  "openapi" : "3.0.1",
  "paths" : {
    "/api/v1/accounts" : {
      "get" : {
        "operationId" : "list_8",
        "responses" : {
          "200" : {
            "content" : {
              "*/*" : {
                "schema" : {
                  "items" : {
                    "$ref" : "#/components/schemas/AccountResponse"
                  },
                  "type" : "array"
                }
              }
            },
            "description" : "OK"
          }
        },
        "security" : [ {
          "bearerAuth" : [ ]
        } ],
        "summary" : "List all accounts for the current user",
        "tags" : [ "Accounts" ]
      },
      "post" : {
        "operationId" : "create_5",
        "parameters" : [ {
          "description" : "Optional client-generated key (16-128 URL-safe characters) that makes a retried create safe to resend; a retry with the same key and payload replays the original result instead of creating a duplicate account.",
          "in" : "header",
          "name" : "Idempotency-Key",
          "required" : false,
          "schema" : {
            "type" : "string"
          }
        } ],
        "requestBody" : {
          "content" : {
            "application/json" : {
              "schema" : {
                "$ref" : "#/components/schemas/CreateAccountRequest"
              }
            }
          },
          "required" : true
        },
        "responses" : {
          "200" : {
            "content" : {
              "*/*" : {
                "schema" : {
                  "$ref" : "#/components/schemas/AccountResponse"
                }
              }
            },
            "description" : "OK"
          }
        },
        "security" : [ {
          "bearerAuth" : [ ]
        } ],
        "summary" : "Create a new account",
        "tags" : [ "Accounts" ]
      }
    },
    "/api/v1/accounts/{id}" : {
      "delete" : {
        "operationId" : "delete_5",
        "parameters" : [ {
          "in" : "path",
          "name" : "id",
          "required" : true,
          "schema" : {
            "format" : "int64",
            "type" : "integer"
          }
        } ],
        "responses" : {
          "204" : {
            "description" : "No Content"
          }
        },
        "security" : [ {
          "bearerAuth" : [ ]
        } ],
        "summary" : "Delete an account and all its connected transactions",
        "tags" : [ "Accounts" ]
      },
      "get" : {
        "operationId" : "getById_4",
        "parameters" : [ {
          "in" : "path",
          "name" : "id",
          "required" : true,
          "schema" : {
            "format" : "int64",
            "type" : "integer"
          }
        } ],
        "responses" : {
          "200" : {
            "content" : {
              "*/*" : {
                "schema" : {
                  "$ref" : "#/components/schemas/AccountResponse"
                }
              }
            },
            "description" : "OK"
          }
        },
        "security" : [ {
          "bearerAuth" : [ ]
        } ],
        "summary" : "Get a single account by id",
        "tags" : [ "Accounts" ]
      },
      "put" : {
        "operationId" : "update_3",
        "parameters" : [ {
          "in" : "path",
          "name" : "id",
          "required" : true,
          "schema" : {
            "format" : "int64",
            "type" : "integer"
          }
        } ],
        "requestBody" : {
          "content" : {
            "application/json" : {
              "schema" : {
                "$ref" : "#/components/schemas/UpdateAccountRequest"
              }
            }
          },
          "required" : true
        },
        "responses" : {
          "200" : {
            "content" : {
              "*/*" : {
                "schema" : {
                  "$ref" : "#/components/schemas/AccountResponse"
                }
              }
            },
            "description" : "OK"
          }
        },
        "security" : [ {
          "bearerAuth" : [ ]
        } ],
        "summary" : "Update an account",
        "tags" : [ "Accounts" ]
      }
    },
    "/api/v1/accounts/{id}/delete-preview" : {
      "get" : {
        "operationId" : "deletePreview",
        "parameters" : [ {
          "in" : "path",
          "name" : "id",
          "required" : true,
          "schema" : {
            "format" : "int64",
            "type" : "integer"
          }
        } ],
        "responses" : {
          "200" : {
            "content" : {
              "*/*" : {
                "schema" : {
                  "$ref" : "#/components/schemas/AccountDeletePreviewDto"
                }
              }
            },
            "description" : "OK"
          }
        },
        "security" : [ {
          "bearerAuth" : [ ]
        } ],
        "summary" : "Preview how many transactions will be removed if account is deleted",
        "tags" : [ "Accounts" ]
      }
    },
    "/api/v1/accounts/{id}/recompute-balance" : {
      "post" : {
        "operationId" : "recomputeBalance",
        "parameters" : [ {
          "in" : "path",
          "name" : "id",
          "required" : true,
          "schema" : {
            "format" : "int64",
            "type" : "integer"
          }
        } ],
        "responses" : {
          "200" : {
            "content" : {
              "*/*" : {
                "schema" : {
                  "$ref" : "#/components/schemas/AccountResponse"
                }
              }
            },
            "description" : "OK"
          }
        },
        "security" : [ {
          "bearerAuth" : [ ]
        } ],
        "summary" : "Recompute account balance from transactions (safety-net)",
        "tags" : [ "Accounts" ]
      }
    },
    "/api/v1/activity" : {
      "get" : {
        "operationId" : "list_7",
        "parameters" : [ {
          "in" : "query",
          "name" : "page",
          "required" : false,
          "schema" : {
            "default" : 0,
            "format" : "int32",
            "type" : "integer"
          }
        }, {
          "in" : "query",
          "name" : "size",
          "required" : false,
          "schema" : {
            "default" : 20,
            "format" : "int32",
            "type" : "integer"
          }
        } ],
        "responses" : {
          "200" : {
            "content" : {
              "*/*" : {
                "schema" : {
                  "$ref" : "#/components/schemas/PageActivityEventResponse"
                }
              }
            },
            "description" : "OK"
          }
        },
        "security" : [ {
          "bearerAuth" : [ ]
        } ],
        "summary" : "List recent activity events for the current user",
        "tags" : [ "Activity" ]
      }
    },
    "/api/v1/agent-runs" : {
      "get" : {
        "operationId" : "list_6",
        "responses" : {
          "200" : {
            "content" : {
              "*/*" : {
                "schema" : {
                  "items" : {
                    "$ref" : "#/components/schemas/AgentRunSummaryResponse"
                  },
                  "type" : "array"
                }
              }
            },
            "description" : "OK"
          }
        },
        "summary" : "List the authenticated user's ingestion runs",
        "tags" : [ "Agent Runs" ]
      },
      "post" : {
        "operationId" : "start",
        "requestBody" : {
          "content" : {
            "application/json" : {
              "schema" : {
                "$ref" : "#/components/schemas/StartAgentRunRequest"
              }
            }
          },
          "required" : true
        },
        "responses" : {
          "200" : {
            "content" : {
              "*/*" : {
                "schema" : {
                  "$ref" : "#/components/schemas/AgentRunSummaryResponse"
                }
              }
            },
            "description" : "OK"
          }
        },
        "summary" : "Start an ingestion run for an owned vault receipt",
        "tags" : [ "Agent Runs" ]
      }
    },
    "/api/v1/agent-runs/{id}" : {
      "get" : {
        "operationId" : "get",
        "parameters" : [ {
          "in" : "path",
          "name" : "id",
          "required" : true,
          "schema" : {
            "format" : "int64",
            "type" : "integer"
          }
        } ],
        "responses" : {
          "200" : {
            "content" : {
              "*/*" : {
                "schema" : {
                  "$ref" : "#/components/schemas/AgentRunDetailResponse"
                }
              }
            },
            "description" : "OK"
          }
        },
        "summary" : "Get an ingestion run's full detail, including proposals",
        "tags" : [ "Agent Runs" ]
      }
    },
    "/api/v1/agent-runs/{id}/commit" : {
      "post" : {
        "operationId" : "commit",
        "parameters" : [ {
          "in" : "path",
          "name" : "id",
          "required" : true,
          "schema" : {
            "format" : "int64",
            "type" : "integer"
          }
        } ],
        "responses" : {
          "200" : {
            "content" : {
              "*/*" : {
                "schema" : {
                  "$ref" : "#/components/schemas/AgentRunDetailResponse"
                }
              }
            },
            "description" : "OK"
          }
        },
        "summary" : "Agent-token or recovery path: commit the run's stored proposals",
        "tags" : [ "Agent Runs" ]
      }
    },
    "/api/v1/agent-runs/{id}/decision" : {
      "post" : {
        "operationId" : "decide",
        "parameters" : [ {
          "in" : "path",
          "name" : "id",
          "required" : true,
          "schema" : {
            "format" : "int64",
            "type" : "integer"
          }
        } ],
        "requestBody" : {
          "content" : {
            "application/json" : {
              "schema" : {
                "$ref" : "#/components/schemas/AgentDecisionRequest"
              }
            }
          },
          "required" : true
        },
        "responses" : {
          "200" : {
            "content" : {
              "*/*" : {
                "schema" : {
                  "$ref" : "#/components/schemas/AgentRunDetailResponse"
                }
              }
            },
            "description" : "OK"
          }
        },
        "summary" : "Approve (with optional edits) or reject a run awaiting review",
        "tags" : [ "Agent Runs" ]
      }
    },
    "/api/v1/agent-runs/{id}/fail" : {
      "post" : {
        "operationId" : "fail",
        "parameters" : [ {
          "in" : "path",
          "name" : "id",
          "required" : true,
          "schema" : {
            "format" : "int64",
            "type" : "integer"
          }
        } ],
        "requestBody" : {
          "content" : {
            "application/json" : {
              "schema" : {
                "$ref" : "#/components/schemas/FailAgentRunRequest"
              }
            }
          },
          "required" : true
        },
        "responses" : {
          "200" : {
            "description" : "OK"
          }
        },
        "summary" : "Agent-token: report that the run could not complete",
        "tags" : [ "Agent Runs" ]
      }
    },
    "/api/v1/agent-runs/{id}/proposals" : {
      "post" : {
        "operationId" : "submitProposals",
        "parameters" : [ {
          "in" : "path",
          "name" : "id",
          "required" : true,
          "schema" : {
            "format" : "int64",
            "type" : "integer"
          }
        } ],
        "requestBody" : {
          "content" : {
            "application/json" : {
              "schema" : {
                "$ref" : "#/components/schemas/SubmitProposalsRequest"
              }
            }
          },
          "required" : true
        },
        "responses" : {
          "200" : {
            "content" : {
              "*/*" : {
                "schema" : {
                  "$ref" : "#/components/schemas/AgentRunDetailResponse"
                }
              }
            },
            "description" : "OK"
          }
        },
        "summary" : "Agent-token: submit extraction + proposals, moving the run to AWAITING_REVIEW",
        "tags" : [ "Agent Runs" ]
      }
    },
    "/api/v1/analytics/balances" : {
      "get" : {
        "operationId" : "balances",
        "parameters" : [ {
          "in" : "query",
          "name" : "targetCurrency",
          "required" : false,
          "schema" : {
            "pattern" : "^[A-Z]{3}$",
            "type" : "string"
          }
        } ],
        "responses" : {
          "200" : {
            "content" : {
              "*/*" : {
                "schema" : {
                  "type" : "object"
                }
              }
            },
            "description" : "OK"
          }
        },
        "security" : [ {
          "bearerAuth" : [ ]
        } ],
        "summary" : "Account balances grouped by currency, with a total per currency; pass targetCurrency to additionally receive a converted grand total",
        "tags" : [ "Analytics" ]
      }
    },
    "/api/v1/analytics/budget-history" : {
      "get" : {
        "operationId" : "budgetHistory",
        "parameters" : [ {
          "in" : "query",
          "name" : "from",
          "required" : true,
          "schema" : {
            "format" : "date",
            "type" : "string"
          }
        }, {
          "in" : "query",
          "name" : "to",
          "required" : true,
          "schema" : {
            "format" : "date",
            "type" : "string"
          }
        }, {
          "in" : "query",
          "name" : "currency",
          "required" : false,
          "schema" : {
            "pattern" : "^[A-Z]{3}$",
            "type" : "string"
          }
        } ],
        "responses" : {
          "200" : {
            "content" : {
              "*/*" : {
                "schema" : {
                  "items" : {
                    "$ref" : "#/components/schemas/BudgetHistoryDto"
                  },
                  "type" : "array"
                }
              }
            },
            "description" : "OK"
          }
        },
        "security" : [ {
          "bearerAuth" : [ ]
        } ],
        "summary" : "Historical budget performance by calendar period and native currency",
        "tags" : [ "Analytics" ]
      }
    },
    "/api/v1/analytics/budget-progress" : {
      "get" : {
        "operationId" : "budgetProgress",
        "responses" : {
          "200" : {
            "content" : {
              "*/*" : {
                "schema" : {
                  "items" : {
                    "$ref" : "#/components/schemas/BudgetProgressDto"
                  },
                  "type" : "array"
                }
              }
            },
            "description" : "OK"
          }
        },
        "security" : [ {
          "bearerAuth" : [ ]
        } ],
        "summary" : "Current period progress for all active budgets",
        "tags" : [ "Analytics" ]
      }
    },
    "/api/v1/analytics/income-vs-expense" : {
      "get" : {
        "operationId" : "incomeVsExpense",
        "parameters" : [ {
          "in" : "query",
          "name" : "from",
          "required" : true,
          "schema" : {
            "format" : "date",
            "type" : "string"
          }
        }, {
          "in" : "query",
          "name" : "to",
          "required" : true,
          "schema" : {
            "format" : "date",
            "type" : "string"
          }
        } ],
        "responses" : {
          "200" : {
            "content" : {
              "*/*" : {
                "schema" : {
                  "items" : {
                    "$ref" : "#/components/schemas/IncomeExpenseTrendDto"
                  },
                  "type" : "array"
                }
              }
            },
            "description" : "OK"
          }
        },
        "security" : [ {
          "bearerAuth" : [ ]
        } ],
        "summary" : "Monthly income vs expense trend for a date range",
        "tags" : [ "Analytics" ]
      }
    },
    "/api/v1/analytics/incoming-transfer-total" : {
      "get" : {
        "operationId" : "incomingTransferTotal",
        "parameters" : [ {
          "in" : "query",
          "name" : "accountId",
          "required" : true,
          "schema" : {
            "format" : "int64",
            "type" : "integer"
          }
        }, {
          "in" : "query",
          "name" : "from",
          "required" : true,
          "schema" : {
            "format" : "date",
            "type" : "string"
          }
        }, {
          "in" : "query",
          "name" : "to",
          "required" : true,
          "schema" : {
            "format" : "date",
            "type" : "string"
          }
        } ],
        "responses" : {
          "200" : {
            "content" : {
              "*/*" : {
                "schema" : {
                  "$ref" : "#/components/schemas/IncomingTransferTotalDto"
                }
              }
            },
            "description" : "OK"
          }
        },
        "security" : [ {
          "bearerAuth" : [ ]
        } ],
        "summary" : "Total incoming transfers into an account for a date range",
        "tags" : [ "Analytics" ]
      }
    },
    "/api/v1/analytics/overview" : {
      "get" : {
        "operationId" : "getOverview",
        "parameters" : [ {
          "in" : "query",
          "name" : "targetCurrency",
          "required" : true,
          "schema" : {
            "pattern" : "^[A-Z]{3}$",
            "type" : "string"
          }
        }, {
          "in" : "query",
          "name" : "from",
          "required" : true,
          "schema" : {
            "format" : "date",
            "type" : "string"
          }
        }, {
          "in" : "query",
          "name" : "to",
          "required" : true,
          "schema" : {
            "format" : "date",
            "type" : "string"
          }
        } ],
        "responses" : {
          "200" : {
            "content" : {
              "*/*" : {
                "schema" : {
                  "$ref" : "#/components/schemas/ConvertedOverviewDto"
                }
              }
            },
            "description" : "OK"
          }
        },
        "security" : [ {
          "bearerAuth" : [ ]
        } ],
        "summary" : "All analytics converted into a single target currency",
        "tags" : [ "Analytics" ]
      }
    },
    "/api/v1/analytics/spending-by-category" : {
      "get" : {
        "operationId" : "spendingByCategory",
        "parameters" : [ {
          "in" : "query",
          "name" : "from",
          "required" : true,
          "schema" : {
            "format" : "date",
            "type" : "string"
          }
        }, {
          "in" : "query",
          "name" : "to",
          "required" : true,
          "schema" : {
            "format" : "date",
            "type" : "string"
          }
        }, {
          "in" : "query",
          "name" : "accountId",
          "required" : false,
          "schema" : {
            "format" : "int64",
            "type" : "integer"
          }
        } ],
        "responses" : {
          "200" : {
            "content" : {
              "*/*" : {
                "schema" : {
                  "items" : {
                    "$ref" : "#/components/schemas/SpendingByCategoryDto"
                  },
                  "type" : "array"
                }
              }
            },
            "description" : "OK"
          }
        },
        "security" : [ {
          "bearerAuth" : [ ]
        } ],
        "summary" : "Spending breakdown by category for a date range, optionally scoped to one account",
        "tags" : [ "Analytics" ]
      }
    },
    "/api/v1/auth/login" : {
      "post" : {
        "operationId" : "login",
        "requestBody" : {
          "content" : {
            "application/json" : {
              "schema" : {
                "$ref" : "#/components/schemas/LoginRequest"
              }
            }
          },
          "required" : true
        },
        "responses" : {
          "200" : {
            "content" : {
              "*/*" : {
                "schema" : {
                  "$ref" : "#/components/schemas/TokenResponse"
                }
              }
            },
            "description" : "OK"
          }
        },
        "summary" : "Login with email + password",
        "tags" : [ "Authentication" ]
      }
    },
    "/api/v1/auth/logout" : {
      "post" : {
        "operationId" : "logout",
        "requestBody" : {
          "content" : {
            "application/json" : {
              "schema" : {
                "$ref" : "#/components/schemas/RefreshRequest"
              }
            }
          },
          "required" : true
        },
        "responses" : {
          "204" : {
            "description" : "No Content"
          }
        },
        "summary" : "Revoke the refresh token (logout)",
        "tags" : [ "Authentication" ]
      }
    },
    "/api/v1/auth/me" : {
      "get" : {
        "operationId" : "me",
        "responses" : {
          "200" : {
            "content" : {
              "*/*" : {
                "schema" : {
                  "$ref" : "#/components/schemas/UserInfo"
                }
              }
            },
            "description" : "OK"
          }
        },
        "security" : [ {
          "bearerAuth" : [ ]
        } ],
        "summary" : "Return current authenticated user info",
        "tags" : [ "Authentication" ]
      }
    },
    "/api/v1/auth/me/changelog-seen" : {
      "put" : {
        "operationId" : "updateChangelogSeen",
        "requestBody" : {
          "content" : {
            "application/json" : {
              "schema" : {
                "$ref" : "#/components/schemas/UpdateChangelogSeenRequest"
              }
            }
          },
          "required" : true
        },
        "responses" : {
          "200" : {
            "content" : {
              "*/*" : {
                "schema" : {
                  "$ref" : "#/components/schemas/UserInfo"
                }
              }
            },
            "description" : "OK"
          }
        },
        "security" : [ {
          "bearerAuth" : [ ]
        } ],
        "summary" : "Mark the authenticated user's last-seen \"What's New\" changelog version",
        "tags" : [ "Authentication" ]
      }
    },
    "/api/v1/auth/me/language" : {
      "put" : {
        "operationId" : "updateLanguage",
        "requestBody" : {
          "content" : {
            "application/json" : {
              "schema" : {
                "$ref" : "#/components/schemas/UpdateLanguageRequest"
              }
            }
          },
          "required" : true
        },
        "responses" : {
          "200" : {
            "content" : {
              "*/*" : {
                "schema" : {
                  "$ref" : "#/components/schemas/UserInfo"
                }
              }
            },
            "description" : "OK"
          }
        },
        "security" : [ {
          "bearerAuth" : [ ]
        } ],
        "summary" : "Update the authenticated user's preferred UI language",
        "tags" : [ "Authentication" ]
      }
    },
    "/api/v1/auth/refresh" : {
      "post" : {
        "operationId" : "refresh",
        "requestBody" : {
          "content" : {
            "application/json" : {
              "schema" : {
                "$ref" : "#/components/schemas/RefreshRequest"
              }
            }
          },
          "required" : true
        },
        "responses" : {
          "200" : {
            "content" : {
              "*/*" : {
                "schema" : {
                  "$ref" : "#/components/schemas/TokenResponse"
                }
              }
            },
            "description" : "OK"
          }
        },
        "summary" : "Rotate refresh token and receive a new access token",
        "tags" : [ "Authentication" ]
      }
    },
    "/api/v1/auth/register" : {
      "post" : {
        "operationId" : "register",
        "requestBody" : {
          "content" : {
            "application/json" : {
              "schema" : {
                "$ref" : "#/components/schemas/RegisterRequest"
              }
            }
          },
          "required" : true
        },
        "responses" : {
          "201" : {
            "content" : {
              "*/*" : {
                "schema" : {
                  "$ref" : "#/components/schemas/TokenResponse"
                }
              }
            },
            "description" : "Created"
          }
        },
        "summary" : "Register a new user and receive tokens",
        "tags" : [ "Authentication" ]
      }
    },
    "/api/v1/budgets" : {
      "get" : {
        "operationId" : "list_5",
        "responses" : {
          "200" : {
            "content" : {
              "*/*" : {
                "schema" : {
                  "items" : {
                    "$ref" : "#/components/schemas/BudgetResponse"
                  },
                  "type" : "array"
                }
              }
            },
            "description" : "OK"
          }
        },
        "security" : [ {
          "bearerAuth" : [ ]
        } ],
        "summary" : "List all budgets with current-period progress",
        "tags" : [ "Budgets" ]
      },
      "post" : {
        "operationId" : "create_4",
        "parameters" : [ {
          "description" : "Optional client-generated key (16-128 URL-safe characters) that makes a retried create safe to resend; a retry with the same key and payload replays the original result instead of creating a duplicate budget.",
          "in" : "header",
          "name" : "Idempotency-Key",
          "required" : false,
          "schema" : {
            "type" : "string"
          }
        } ],
        "requestBody" : {
          "content" : {
            "application/json" : {
              "schema" : {
                "$ref" : "#/components/schemas/CreateBudgetRequest"
              }
            }
          },
          "required" : true
        },
        "responses" : {
          "200" : {
            "content" : {
              "*/*" : {
                "schema" : {
                  "$ref" : "#/components/schemas/BudgetResponse"
                }
              }
            },
            "description" : "OK"
          }
        },
        "security" : [ {
          "bearerAuth" : [ ]
        } ],
        "summary" : "Create a budget for a category and period",
        "tags" : [ "Budgets" ]
      }
    },
    "/api/v1/budgets/{id}" : {
      "delete" : {
        "operationId" : "delete_4",
        "parameters" : [ {
          "in" : "path",
          "name" : "id",
          "required" : true,
          "schema" : {
            "format" : "int64",
            "type" : "integer"
          }
        } ],
        "responses" : {
          "204" : {
            "description" : "No Content"
          }
        },
        "security" : [ {
          "bearerAuth" : [ ]
        } ],
        "summary" : "Delete a budget (transactions unaffected)",
        "tags" : [ "Budgets" ]
      },
      "get" : {
        "operationId" : "getById_3",
        "parameters" : [ {
          "in" : "path",
          "name" : "id",
          "required" : true,
          "schema" : {
            "format" : "int64",
            "type" : "integer"
          }
        } ],
        "responses" : {
          "200" : {
            "content" : {
              "*/*" : {
                "schema" : {
                  "$ref" : "#/components/schemas/BudgetResponse"
                }
              }
            },
            "description" : "OK"
          }
        },
        "security" : [ {
          "bearerAuth" : [ ]
        } ],
        "summary" : "Get a single budget with progress",
        "tags" : [ "Budgets" ]
      },
      "put" : {
        "operationId" : "update_2",
        "parameters" : [ {
          "in" : "path",
          "name" : "id",
          "required" : true,
          "schema" : {
            "format" : "int64",
            "type" : "integer"
          }
        } ],
        "requestBody" : {
          "content" : {
            "application/json" : {
              "schema" : {
                "$ref" : "#/components/schemas/UpdateBudgetRequest"
              }
            }
          },
          "required" : true
        },
        "responses" : {
          "200" : {
            "content" : {
              "*/*" : {
                "schema" : {
                  "$ref" : "#/components/schemas/BudgetResponse"
                }
              }
            },
            "description" : "OK"
          }
        },
        "security" : [ {
          "bearerAuth" : [ ]
        } ],
        "summary" : "Update budget limit or period",
        "tags" : [ "Budgets" ]
      }
    },
    "/api/v1/categories" : {
      "get" : {
        "operationId" : "list_4",
        "parameters" : [ {
          "in" : "query",
          "name" : "type",
          "required" : false,
          "schema" : {
            "enum" : [ "INCOME", "EXPENSE", "TRANSFER" ],
            "type" : "string"
          }
        } ],
        "responses" : {
          "200" : {
            "content" : {
              "*/*" : {
                "schema" : {
                  "items" : {
                    "$ref" : "#/components/schemas/CategoryResponse"
                  },
                  "type" : "array"
                }
              }
            },
            "description" : "OK"
          }
        },
        "security" : [ {
          "bearerAuth" : [ ]
        } ],
        "summary" : "List categories (system defaults + user-defined), optionally filtered by type",
        "tags" : [ "Categories" ]
      },
      "post" : {
        "operationId" : "create_3",
        "parameters" : [ {
          "description" : "Optional client-generated key (16-128 URL-safe characters) that makes a retried create safe to resend; a retry with the same key and payload replays the original result instead of creating a duplicate category.",
          "in" : "header",
          "name" : "Idempotency-Key",
          "required" : false,
          "schema" : {
            "type" : "string"
          }
        } ],
        "requestBody" : {
          "content" : {
            "application/json" : {
              "schema" : {
                "$ref" : "#/components/schemas/CreateCategoryRequest"
              }
            }
          },
          "required" : true
        },
        "responses" : {
          "200" : {
            "content" : {
              "*/*" : {
                "schema" : {
                  "$ref" : "#/components/schemas/CategoryResponse"
                }
              }
            },
            "description" : "OK"
          }
        },
        "security" : [ {
          "bearerAuth" : [ ]
        } ],
        "summary" : "Create a user-defined category",
        "tags" : [ "Categories" ]
      }
    },
    "/api/v1/categories/{id}" : {
      "delete" : {
        "operationId" : "delete_3",
        "parameters" : [ {
          "in" : "path",
          "name" : "id",
          "required" : true,
          "schema" : {
            "format" : "int64",
            "type" : "integer"
          }
        } ],
        "responses" : {
          "204" : {
            "description" : "No Content"
          }
        },
        "security" : [ {
          "bearerAuth" : [ ]
        } ],
        "summary" : "Delete a user-defined category (transactions reassigned to Uncategorized)",
        "tags" : [ "Categories" ]
      },
      "put" : {
        "operationId" : "update_1",
        "parameters" : [ {
          "in" : "path",
          "name" : "id",
          "required" : true,
          "schema" : {
            "format" : "int64",
            "type" : "integer"
          }
        } ],
        "requestBody" : {
          "content" : {
            "application/json" : {
              "schema" : {
                "$ref" : "#/components/schemas/UpdateCategoryRequest"
              }
            }
          },
          "required" : true
        },
        "responses" : {
          "200" : {
            "content" : {
              "*/*" : {
                "schema" : {
                  "$ref" : "#/components/schemas/CategoryResponse"
                }
              }
            },
            "description" : "OK"
          }
        },
        "security" : [ {
          "bearerAuth" : [ ]
        } ],
        "summary" : "Rename a user-defined category (system categories return 403)",
        "tags" : [ "Categories" ]
      }
    },
    "/api/v1/exchange-rates/convert" : {
      "get" : {
        "operationId" : "convert",
        "parameters" : [ {
          "in" : "query",
          "name" : "from",
          "required" : true,
          "schema" : {
            "type" : "string"
          }
        }, {
          "in" : "query",
          "name" : "to",
          "required" : true,
          "schema" : {
            "type" : "string"
          }
        }, {
          "in" : "query",
          "name" : "amount",
          "required" : true,
          "schema" : {
            "exclusiveMinimum" : false,
            "minimum" : 0.01,
            "type" : "number"
          }
        } ],
        "responses" : {
          "200" : {
            "content" : {
              "*/*" : {
                "schema" : {
                  "$ref" : "#/components/schemas/ConvertResponse"
                }
              }
            },
            "description" : "OK"
          }
        },
        "security" : [ {
          "bearerAuth" : [ ]
        } ],
        "summary" : "Convert an amount between two currencies using cached exchange rates",
        "tags" : [ "Exchange Rates" ]
      }
    },
    "/api/v1/recurring-transactions" : {
      "get" : {
        "operationId" : "list_3",
        "responses" : {
          "200" : {
            "content" : {
              "*/*" : {
                "schema" : {
                  "items" : {
                    "$ref" : "#/components/schemas/RecurringResponse"
                  },
                  "type" : "array"
                }
              }
            },
            "description" : "OK"
          }
        },
        "security" : [ {
          "bearerAuth" : [ ]
        } ],
        "summary" : "List all recurring transaction definitions",
        "tags" : [ "Recurring Transactions" ]
      },
      "post" : {
        "operationId" : "create_2",
        "parameters" : [ {
          "description" : "Optional client-generated key (16-128 URL-safe characters) that makes a retried create safe to resend; a retry with the same key and payload replays the original result instead of creating a duplicate recurring definition.",
          "in" : "header",
          "name" : "Idempotency-Key",
          "required" : false,
          "schema" : {
            "type" : "string"
          }
        } ],
        "requestBody" : {
          "content" : {
            "application/json" : {
              "schema" : {
                "$ref" : "#/components/schemas/CreateRecurringRequest"
              }
            }
          },
          "required" : true
        },
        "responses" : {
          "200" : {
            "content" : {
              "*/*" : {
                "schema" : {
                  "$ref" : "#/components/schemas/RecurringResponse"
                }
              }
            },
            "description" : "OK"
          }
        },
        "security" : [ {
          "bearerAuth" : [ ]
        } ],
        "summary" : "Create a recurring transaction definition",
        "tags" : [ "Recurring Transactions" ]
      }
    },
    "/api/v1/recurring-transactions/{id}" : {
      "delete" : {
        "operationId" : "delete_2",
        "parameters" : [ {
          "in" : "path",
          "name" : "id",
          "required" : true,
          "schema" : {
            "format" : "int64",
            "type" : "integer"
          }
        } ],
        "responses" : {
          "204" : {
            "description" : "No Content"
          }
        },
        "security" : [ {
          "bearerAuth" : [ ]
        } ],
        "summary" : "Delete a definition (already-generated transactions are retained)",
        "tags" : [ "Recurring Transactions" ]
      },
      "get" : {
        "operationId" : "getById_2",
        "parameters" : [ {
          "in" : "path",
          "name" : "id",
          "required" : true,
          "schema" : {
            "format" : "int64",
            "type" : "integer"
          }
        } ],
        "responses" : {
          "200" : {
            "content" : {
              "*/*" : {
                "schema" : {
                  "$ref" : "#/components/schemas/RecurringResponse"
                }
              }
            },
            "description" : "OK"
          }
        },
        "security" : [ {
          "bearerAuth" : [ ]
        } ],
        "summary" : "Get a recurring definition by id",
        "tags" : [ "Recurring Transactions" ]
      }
    },
    "/api/v1/recurring-transactions/{id}/pause" : {
      "post" : {
        "operationId" : "pause",
        "parameters" : [ {
          "in" : "path",
          "name" : "id",
          "required" : true,
          "schema" : {
            "format" : "int64",
            "type" : "integer"
          }
        } ],
        "responses" : {
          "200" : {
            "content" : {
              "*/*" : {
                "schema" : {
                  "$ref" : "#/components/schemas/RecurringResponse"
                }
              }
            },
            "description" : "OK"
          }
        },
        "security" : [ {
          "bearerAuth" : [ ]
        } ],
        "summary" : "Pause a recurring definition — stops future generation",
        "tags" : [ "Recurring Transactions" ]
      }
    },
    "/api/v1/recurring-transactions/{id}/resume" : {
      "post" : {
        "operationId" : "resume",
        "parameters" : [ {
          "in" : "path",
          "name" : "id",
          "required" : true,
          "schema" : {
            "format" : "int64",
            "type" : "integer"
          }
        } ],
        "responses" : {
          "200" : {
            "content" : {
              "*/*" : {
                "schema" : {
                  "$ref" : "#/components/schemas/RecurringResponse"
                }
              }
            },
            "description" : "OK"
          }
        },
        "security" : [ {
          "bearerAuth" : [ ]
        } ],
        "summary" : "Resume a paused recurring definition",
        "tags" : [ "Recurring Transactions" ]
      }
    },
    "/api/v1/tokens" : {
      "get" : {
        "operationId" : "list_2",
        "responses" : {
          "200" : {
            "content" : {
              "*/*" : {
                "schema" : {
                  "items" : {
                    "$ref" : "#/components/schemas/ApiTokenResponse"
                  },
                  "type" : "array"
                }
              }
            },
            "description" : "OK"
          }
        },
        "security" : [ {
          "bearerAuth" : [ ]
        } ],
        "summary" : "List your API tokens",
        "tags" : [ "API Tokens" ]
      },
      "post" : {
        "operationId" : "create_1",
        "parameters" : [ {
          "description" : "Optional client-generated key (16-128 URL-safe characters) that makes a retried create safe to resend; because the plaintext token can never be persisted or replayed, a retry with this key always gets a typed 409 with the original token's metadata instead of creating a second token.",
          "in" : "header",
          "name" : "Idempotency-Key",
          "required" : false,
          "schema" : {
            "type" : "string"
          }
        } ],
        "requestBody" : {
          "content" : {
            "application/json" : {
              "schema" : {
                "$ref" : "#/components/schemas/CreateApiTokenRequest"
              }
            }
          },
          "required" : true
        },
        "responses" : {
          "200" : {
            "content" : {
              "*/*" : {
                "schema" : {
                  "$ref" : "#/components/schemas/CreatedApiTokenResponse"
                }
              }
            },
            "description" : "OK"
          }
        },
        "security" : [ {
          "bearerAuth" : [ ]
        } ],
        "summary" : "Create a personal access token (plaintext returned once)",
        "tags" : [ "API Tokens" ]
      }
    },
    "/api/v1/tokens/{id}" : {
      "delete" : {
        "operationId" : "revoke",
        "parameters" : [ {
          "in" : "path",
          "name" : "id",
          "required" : true,
          "schema" : {
            "format" : "int64",
            "type" : "integer"
          }
        } ],
        "responses" : {
          "204" : {
            "description" : "No Content"
          }
        },
        "security" : [ {
          "bearerAuth" : [ ]
        } ],
        "summary" : "Revoke an API token",
        "tags" : [ "API Tokens" ]
      }
    },
    "/api/v1/transactions" : {
      "get" : {
        "operationId" : "list_1",
        "parameters" : [ {
          "in" : "query",
          "name" : "accountId",
          "required" : false,
          "schema" : {
            "format" : "int64",
            "type" : "integer"
          }
        }, {
          "in" : "query",
          "name" : "startDate",
          "required" : false,
          "schema" : {
            "format" : "date",
            "type" : "string"
          }
        }, {
          "in" : "query",
          "name" : "endDate",
          "required" : false,
          "schema" : {
            "format" : "date",
            "type" : "string"
          }
        }, {
          "in" : "query",
          "name" : "categoryId",
          "required" : false,
          "schema" : {
            "format" : "int64",
            "type" : "integer"
          }
        }, {
          "in" : "query",
          "name" : "type",
          "required" : false,
          "schema" : {
            "enum" : [ "INCOME", "EXPENSE", "TRANSFER" ],
            "type" : "string"
          }
        }, {
          "in" : "query",
          "name" : "note",
          "required" : false,
          "schema" : {
            "type" : "string"
          }
        }, {
          "in" : "query",
          "name" : "transferAccountId",
          "required" : false,
          "schema" : {
            "format" : "int64",
            "type" : "integer"
          }
        }, {
          "in" : "query",
          "name" : "currency",
          "required" : false,
          "schema" : {
            "type" : "string"
          }
        }, {
          "in" : "query",
          "name" : "page",
          "required" : false,
          "schema" : {
            "default" : 0,
            "format" : "int32",
            "type" : "integer"
          }
        }, {
          "in" : "query",
          "name" : "size",
          "required" : false,
          "schema" : {
            "default" : 20,
            "format" : "int32",
            "type" : "integer"
          }
        }, {
          "in" : "query",
          "name" : "sortBy",
          "required" : false,
          "schema" : {
            "type" : "string"
          }
        }, {
          "in" : "query",
          "name" : "sortDir",
          "required" : false,
          "schema" : {
            "default" : "desc",
            "type" : "string"
          }
        } ],
        "responses" : {
          "200" : {
            "content" : {
              "*/*" : {
                "schema" : {
                  "$ref" : "#/components/schemas/PageResponseTransactionResponse"
                }
              }
            },
            "description" : "OK"
          }
        },
        "security" : [ {
          "bearerAuth" : [ ]
        } ],
        "summary" : "List transactions with optional filters (defaults to all accounts)",
        "tags" : [ "Transactions" ]
      },
      "post" : {
        "operationId" : "create",
        "parameters" : [ {
          "description" : "Optional client-generated key (16-128 URL-safe characters) that makes a retried create safe to resend; a retry with the same key and payload replays the original result instead of creating a duplicate transaction/balance effect.",
          "in" : "header",
          "name" : "Idempotency-Key",
          "required" : false,
          "schema" : {
            "type" : "string"
          }
        } ],
        "requestBody" : {
          "content" : {
            "application/json" : {
              "schema" : {
                "$ref" : "#/components/schemas/CreateTransactionRequest"
              }
            }
          },
          "required" : true
        },
        "responses" : {
          "200" : {
            "content" : {
              "*/*" : {
                "schema" : {
                  "$ref" : "#/components/schemas/TransactionResponse"
                }
              }
            },
            "description" : "OK"
          }
        },
        "security" : [ {
          "bearerAuth" : [ ]
        } ],
        "summary" : "Create a transaction (INCOME, EXPENSE, or TRANSFER)",
        "tags" : [ "Transactions" ]
      }
    },
    "/api/v1/transactions/batch" : {
      "post" : {
        "operationId" : "createBatch",
        "parameters" : [ {
          "description" : "Required client-generated key (16-128 URL-safe characters) scoping the whole batch request; resubmitting the same key and payload resumes an interrupted batch or replays the original per-row outcomes instead of reprocessing already-completed rows.",
          "in" : "header",
          "name" : "Idempotency-Key",
          "required" : false,
          "schema" : {
            "type" : "string"
          }
        } ],
        "requestBody" : {
          "content" : {
            "application/json" : {
              "schema" : {
                "$ref" : "#/components/schemas/BatchTransactionRequest"
              }
            }
          },
          "required" : true
        },
        "responses" : {
          "200" : {
            "content" : {
              "*/*" : {
                "schema" : {
                  "$ref" : "#/components/schemas/BatchTransactionResponse"
                }
              }
            },
            "description" : "OK"
          }
        },
        "security" : [ {
          "bearerAuth" : [ ]
        } ],
        "summary" : "Create transactions independently and return a result for every row",
        "tags" : [ "Transactions" ]
      }
    },
    "/api/v1/transactions/{id}" : {
      "delete" : {
        "operationId" : "delete_1",
        "parameters" : [ {
          "in" : "path",
          "name" : "id",
          "required" : true,
          "schema" : {
            "format" : "int64",
            "type" : "integer"
          }
        } ],
        "responses" : {
          "204" : {
            "description" : "No Content"
          }
        },
        "security" : [ {
          "bearerAuth" : [ ]
        } ],
        "summary" : "Delete a transaction and reverse its balance effect",
        "tags" : [ "Transactions" ]
      },
      "get" : {
        "operationId" : "getById_1",
        "parameters" : [ {
          "in" : "path",
          "name" : "id",
          "required" : true,
          "schema" : {
            "format" : "int64",
            "type" : "integer"
          }
        } ],
        "responses" : {
          "200" : {
            "content" : {
              "*/*" : {
                "schema" : {
                  "$ref" : "#/components/schemas/TransactionResponse"
                }
              }
            },
            "description" : "OK"
          }
        },
        "security" : [ {
          "bearerAuth" : [ ]
        } ],
        "summary" : "Get a single transaction by id",
        "tags" : [ "Transactions" ]
      },
      "put" : {
        "operationId" : "update",
        "parameters" : [ {
          "in" : "path",
          "name" : "id",
          "required" : true,
          "schema" : {
            "format" : "int64",
            "type" : "integer"
          }
        } ],
        "requestBody" : {
          "content" : {
            "application/json" : {
              "schema" : {
                "$ref" : "#/components/schemas/UpdateTransactionRequest"
              }
            }
          },
          "required" : true
        },
        "responses" : {
          "200" : {
            "content" : {
              "*/*" : {
                "schema" : {
                  "$ref" : "#/components/schemas/TransactionResponse"
                }
              }
            },
            "description" : "OK"
          }
        },
        "security" : [ {
          "bearerAuth" : [ ]
        } ],
        "summary" : "Update a transaction (amount, date, category, note)",
        "tags" : [ "Transactions" ]
      }
    },
    "/api/vault" : {
      "get" : {
        "operationId" : "list",
        "parameters" : [ {
          "in" : "query",
          "name" : "pageable",
          "required" : true,
          "schema" : {
            "$ref" : "#/components/schemas/Pageable"
          }
        } ],
        "responses" : {
          "200" : {
            "content" : {
              "*/*" : {
                "schema" : {
                  "$ref" : "#/components/schemas/PageVaultDocumentResponse"
                }
              }
            },
            "description" : "OK"
          }
        },
        "tags" : [ "vault-controller" ]
      }
    },
    "/api/vault/by-transactions" : {
      "post" : {
        "operationId" : "byTransactions",
        "requestBody" : {
          "content" : {
            "application/json" : {
              "schema" : {
                "items" : {
                  "format" : "int64",
                  "type" : "integer"
                },
                "type" : "array"
              }
            }
          },
          "required" : true
        },
        "responses" : {
          "200" : {
            "content" : {
              "*/*" : {
                "schema" : {
                  "items" : {
                    "$ref" : "#/components/schemas/VaultDocumentResponse"
                  },
                  "type" : "array"
                }
              }
            },
            "description" : "OK"
          }
        },
        "tags" : [ "vault-controller" ]
      }
    },
    "/api/vault/import/upload" : {
      "post" : {
        "operationId" : "upload_1",
        "parameters" : [ {
          "in" : "query",
          "name" : "accountId",
          "required" : true,
          "schema" : {
            "format" : "int64",
            "type" : "integer"
          }
        }, {
          "description" : "Client-generated key (16-128 URL-safe characters) required for every statement upload; a retry with the same key, account, and file replays the original staged document instead of storing a duplicate binary.",
          "in" : "header",
          "name" : "Idempotency-Key",
          "required" : true,
          "schema" : {
            "type" : "string"
          }
        } ],
        "requestBody" : {
          "content" : {
            "multipart/form-data" : {
              "schema" : {
                "properties" : {
                  "file" : {
                    "format" : "binary",
                    "type" : "string"
                  }
                },
                "required" : [ "file" ],
                "type" : "object"
              }
            }
          }
        },
        "responses" : {
          "200" : {
            "content" : {
              "*/*" : {
                "schema" : {
                  "additionalProperties" : {
                    "type" : "string"
                  },
                  "type" : "object"
                }
              }
            },
            "description" : "OK"
          }
        },
        "tags" : [ "statement-import-controller" ]
      }
    },
    "/api/vault/import/{documentId}/confirm" : {
      "post" : {
        "operationId" : "confirm",
        "parameters" : [ {
          "in" : "path",
          "name" : "documentId",
          "required" : true,
          "schema" : {
            "type" : "string"
          }
        }, {
          "description" : "Client-generated key (16-128 URL-safe characters) required for every statement confirmation; a retry with the same key and the same selected-row set resumes or replays the durable per-row result instead of 404ing or creating duplicate transactions. A different selected-row set under the same key returns 409.",
          "in" : "header",
          "name" : "Idempotency-Key",
          "required" : true,
          "schema" : {
            "type" : "string"
          }
        } ],
        "requestBody" : {
          "content" : {
            "application/json" : {
              "schema" : {
                "$ref" : "#/components/schemas/ConfirmImportRequest"
              }
            }
          },
          "required" : true
        },
        "responses" : {
          "200" : {
            "content" : {
              "*/*" : {
                "schema" : {
                  "$ref" : "#/components/schemas/ConfirmImportResponse"
                }
              }
            },
            "description" : "OK"
          }
        },
        "tags" : [ "statement-import-controller" ]
      }
    },
    "/api/vault/import/{documentId}/rows" : {
      "get" : {
        "operationId" : "getReviewRows",
        "parameters" : [ {
          "in" : "path",
          "name" : "documentId",
          "required" : true,
          "schema" : {
            "type" : "string"
          }
        } ],
        "responses" : {
          "200" : {
            "content" : {
              "*/*" : {
                "schema" : {
                  "items" : {
                    "$ref" : "#/components/schemas/StagedRowResponse"
                  },
                  "type" : "array"
                }
              }
            },
            "description" : "OK"
          }
        },
        "tags" : [ "statement-import-controller" ]
      }
    },
    "/api/vault/search" : {
      "post" : {
        "operationId" : "search",
        "parameters" : [ {
          "in" : "query",
          "name" : "pageable",
          "required" : true,
          "schema" : {
            "$ref" : "#/components/schemas/Pageable"
          }
        } ],
        "requestBody" : {
          "content" : {
            "application/json" : {
              "schema" : {
                "$ref" : "#/components/schemas/VaultSearchRequest"
              }
            }
          },
          "required" : true
        },
        "responses" : {
          "200" : {
            "content" : {
              "*/*" : {
                "schema" : {
                  "$ref" : "#/components/schemas/PageVaultDocumentResponse"
                }
              }
            },
            "description" : "OK"
          }
        },
        "tags" : [ "vault-controller" ]
      }
    },
    "/api/vault/upload" : {
      "post" : {
        "operationId" : "upload",
        "parameters" : [ {
          "in" : "query",
          "name" : "type",
          "required" : true,
          "schema" : {
            "enum" : [ "RECEIPT", "STATEMENT" ],
            "type" : "string"
          }
        }, {
          "description" : "Client-generated key (16-128 URL-safe characters) required for every vault upload; a retry with the same key and file replays the original document instead of storing a duplicate binary.",
          "in" : "header",
          "name" : "Idempotency-Key",
          "required" : true,
          "schema" : {
            "type" : "string"
          }
        } ],
        "requestBody" : {
          "content" : {
            "multipart/form-data" : {
              "schema" : {
                "properties" : {
                  "file" : {
                    "format" : "binary",
                    "type" : "string"
                  }
                },
                "required" : [ "file" ],
                "type" : "object"
              }
            }
          }
        },
        "responses" : {
          "200" : {
            "content" : {
              "*/*" : {
                "schema" : {
                  "$ref" : "#/components/schemas/VaultDocumentResponse"
                }
              }
            },
            "description" : "OK"
          }
        },
        "tags" : [ "vault-controller" ]
      }
    },
    "/api/vault/{id}" : {
      "delete" : {
        "operationId" : "delete",
        "parameters" : [ {
          "in" : "path",
          "name" : "id",
          "required" : true,
          "schema" : {
            "type" : "string"
          }
        } ],
        "responses" : {
          "204" : {
            "description" : "No Content"
          }
        },
        "tags" : [ "vault-controller" ]
      },
      "get" : {
        "operationId" : "getById",
        "parameters" : [ {
          "in" : "path",
          "name" : "id",
          "required" : true,
          "schema" : {
            "type" : "string"
          }
        } ],
        "responses" : {
          "200" : {
            "content" : {
              "*/*" : {
                "schema" : {
                  "$ref" : "#/components/schemas/VaultDocumentResponse"
                }
              }
            },
            "description" : "OK"
          }
        },
        "tags" : [ "vault-controller" ]
      }
    },
    "/api/vault/{id}/download" : {
      "get" : {
        "operationId" : "download",
        "parameters" : [ {
          "in" : "path",
          "name" : "id",
          "required" : true,
          "schema" : {
            "type" : "string"
          }
        } ],
        "responses" : {
          "200" : {
            "content" : {
              "*/*" : {
                "schema" : {
                  "format" : "binary",
                  "type" : "string"
                }
              }
            },
            "description" : "OK"
          }
        },
        "tags" : [ "vault-controller" ]
      }
    },
    "/api/vault/{id}/link" : {
      "patch" : {
        "operationId" : "linkToTransaction",
        "parameters" : [ {
          "in" : "path",
          "name" : "id",
          "required" : true,
          "schema" : {
            "type" : "string"
          }
        }, {
          "in" : "query",
          "name" : "transactionId",
          "required" : true,
          "schema" : {
            "format" : "int64",
            "type" : "integer"
          }
        } ],
        "responses" : {
          "200" : {
            "content" : {
              "*/*" : {
                "schema" : {
                  "$ref" : "#/components/schemas/VaultDocumentResponse"
                }
              }
            },
            "description" : "OK"
          }
        },
        "tags" : [ "vault-controller" ]
      }
    }
  },
  "tags" : [ {
    "description" : "Register, login, token refresh and logout",
    "name" : "Authentication"
  }, {
    "description" : "Receipt ingestion agent run lifecycle",
    "name" : "Agent Runs"
  } ]
}